{"cameraMode":{"drawMode":0,"name":"Shaded","section":"Shading Mode"},"sceneLighting":true,"audioPlay":false,"sceneViewState":{"showFog":true,"showMaterialUpdate":false,"showSkybox":true,"showFlares":true,"showImageEffects":true,"showParticleSystems":true},"in2DMode":false,"pivot":{"x":-0.003062695264816284,"y":0.8777625560760498,"z":0.9753761291503906},"rotation":{"x":0.2058083415031433,"y":-0.01437830924987793,"z":0.003009563544765115,"w":0.9784937500953674},"size":1.5653233528137208,"orthographic":false}